XiguanZhifuRenshengShijianban/README.md
XiguanZhifuRenshengShijianban/__init__.py
XiguanZhifuRenshengShijianban/__main__.py
XiguanZhifuRenshengShijianban/file.epub
XiguanZhifuRenshengShijianban/index.html
XiguanZhifuRenshengShijianban/css/__init__.py
XiguanZhifuRenshengShijianban/css/annotations.css
XiguanZhifuRenshengShijianban/css/main.css
XiguanZhifuRenshengShijianban/css/normalize.css
XiguanZhifuRenshengShijianban/css/popup.css
XiguanZhifuRenshengShijianban/font/__init__.py
XiguanZhifuRenshengShijianban/font/fontello.eot
XiguanZhifuRenshengShijianban/font/fontello.svg
XiguanZhifuRenshengShijianban/font/fontello.ttf
XiguanZhifuRenshengShijianban/font/fontello.woff
XiguanZhifuRenshengShijianban/img/__init__.py
XiguanZhifuRenshengShijianban/img/annotator-glyph-sprite.png
XiguanZhifuRenshengShijianban/img/annotator-icon-sprite.png
XiguanZhifuRenshengShijianban/img/apple-touch-icon.png
XiguanZhifuRenshengShijianban/img/cancelfullscreen.png
XiguanZhifuRenshengShijianban/img/close.png
XiguanZhifuRenshengShijianban/img/fullscreen.png
XiguanZhifuRenshengShijianban/img/loader.gif
XiguanZhifuRenshengShijianban/img/menu-icon.png
XiguanZhifuRenshengShijianban/img/save.png
XiguanZhifuRenshengShijianban/img/saved.png
XiguanZhifuRenshengShijianban/img/settings-s.png
XiguanZhifuRenshengShijianban/img/settings.png
XiguanZhifuRenshengShijianban/img/star.png
XiguanZhifuRenshengShijianban/js/__init__.py
XiguanZhifuRenshengShijianban/js/epub.js
XiguanZhifuRenshengShijianban/js/epub.min.js
XiguanZhifuRenshengShijianban/js/epub.min.map
XiguanZhifuRenshengShijianban/js/hooks.min.js
XiguanZhifuRenshengShijianban/js/hooks.min.map
XiguanZhifuRenshengShijianban/js/reader.js
XiguanZhifuRenshengShijianban/js/reader.js.map
XiguanZhifuRenshengShijianban/js/reader.min.js
XiguanZhifuRenshengShijianban/js/reader.min.map
XiguanZhifuRenshengShijianban/js/hooks/__init__.py
XiguanZhifuRenshengShijianban/js/hooks/extensions/__init__.py
XiguanZhifuRenshengShijianban/js/hooks/extensions/highlight.js
xiguan_zhifu_rensheng_shijianban-2022.10.15.0.dist-info/METADATA
xiguan_zhifu_rensheng_shijianban-2022.10.15.0.dist-info/WHEEL
xiguan_zhifu_rensheng_shijianban-2022.10.15.0.dist-info/entry_points.txt
xiguan_zhifu_rensheng_shijianban-2022.10.15.0.dist-info/top_level.txt
xiguan_zhifu_rensheng_shijianban-2022.10.15.0.dist-info/RECORD
